{
  "Scene": "Intersection",
  "TimeOfDay": "Daytime",
  "Weather": "Clear",
  "RoadConditions": "Dry",
  "LaneInformation": {
    "NumberOfLanes": "MultipleLanes",
    "LaneMarkings": "LaneVisible",
    "SpecialLanes": [
      "Crosswalk"
    ]
  },
  "TrafficSigns": {
    "TrafficSignsTypes": [
      "Traffic Light",
      "Bike Lane Sign"
    ],
    "TrafficSignsVisibility": "SignVisible",
    "TrafficLightState": "Red"
  },
  "Vehicles": {
    "TotalNumber": "Few",
    "VehicleTypes": [
      "Van",
      "Sedan"
    ],
    "InMotion": [
      "True"
    ],
    "States": [
      "In Motion",
      "Turning Left"
    ]
  },
  "Pedestrians": [
    "Crossing Street"
  ],
  "Directionality": "Multi-directional with median",
  "Visibility": {
    "General": "Good",
    "SpecificImpairments": [
      "NoImpairments"
    ]
  },
  "Ego-Vehicle": {
    "Direction": "EgoStopped at Intersection",
    "Maneuver": "EgoFullStopped"
  },
  "CameraCondition": "Clear",
  "Severity": 7
}
