{
  "Scene": "Urban",
  "TimeOfDay": "Daytime",
  "Weather": "Clear",
  "RoadConditions": "Dry",
  "LaneInformation": {
    "NumberOfLanes": "3",
    "LaneMarkings": "LaneVisible",
    "SpecialLanes": [
      "Bike Lane"
    ]
  },
  "TrafficSigns": {
    "TrafficSignsTypes": [
      "NoTrafficSigns"
    ],
    "TrafficSignsVisibility": "SignNotVisible"
  },
  "Vehicles": {
    "TotalNumber": "MultipleVehicles",
    "VehicleTypes": [
      "Sedan",
      "SUV",
      "Van"
    ],
    "InMotion": [
      "True"
    ],
    "States": [
      "In Motion"
    ]
  },
  "Pedestrians": [
    "NoPed"
  ],
  "Directionality": "Two-Way",
  "Visibility": {
    "General": "Good",
    "SpecificImpairments": [
      "Camera Glare"
    ]
  },
  "Ego-Vehicle": {
    "Direction": "EgoForward",
    "Maneuver": "EgoMoving"
  },
  "CameraCondition": "Glare",
  "Severity": 3
}
