{
  "Scene": "Urban",
  "TimeOfDay": "Daytime",
  "Weather": "Rainy",
  "RoadConditions": "Wet",
  "LaneInformation": {
    "NumberOfLanes": "2",
    "LaneMarkings": "LaneVisible",
    "SpecialLanes": [
      "NoSpecialLanes"
    ]
  },
  "TrafficSigns": {
    "TrafficSignsTypes": [
      "Traffic Light"
    ],
    "TrafficSignsVisibility": "SignVisible",
    "TrafficLightState": "Green"
  },
  "Vehicles": {
    "TotalNumber": "MultipleVehicles",
    "VehicleTypes": [
      "Cars",
      "Pickup Truck",
      "Bus"
    ],
    "InMotion": [
      "True"
    ],
    "States": [
      "In Motion"
    ]
  },
  "Pedestrians": [
    "NoPed"
  ],
  "Directionality": "Two-Way",
  "Visibility": {
    "General": "Reduced",
    "SpecificImpairments": [
      "Obstructed by Rain"
    ]
  },
  "Ego-Vehicle": {
    "Direction": "EgoApproaching Intersection",
    "Maneuver": "EgoMoving"
  },
  "CameraCondition": "RainOnLens",
  "Severity": 6
}
