{
  "Scene": "Urban",
  "TimeOfDay": "Daytime",
  "Weather": "Rainy",
  "RoadConditions": "Wet",
  "LaneInformation": {
    "NumberOfLanes": "2",
    "LaneMarkings": "LaneVisible",
    "SpecialLanes": [
      "Taxi and Bus Lane"
    ]
  },
  "TrafficSigns": {
    "TrafficSignsTypes": [
      "Traffic Light",
      "One Way Sign",
      "Bus Lane"
    ],
    "TrafficSignsVisibility": "SignVisible",
    "TrafficLightState": "Green"
  },
  "Vehicles": {
    "TotalNumber": "MultipleVehicles",
    "VehicleTypes": [
      "SUV",
      "Sedan"
    ],
    "InMotion": [
      "True"
    ],
    "States": [
      "In Motion"
    ]
  },
  "Pedestrians": [
    "Visible on Sidewalk"
  ],
  "Directionality": "Two-Way",
  "Visibility": {
    "General": "Reduced",
    "SpecificImpairments": [
      "Obstructed by Rain",
      "Camera Glare"
    ]
  },
  "Ego-Vehicle": {
    "Direction": "EgoForward",
    "Maneuver": "EgoMoving"
  },
  "CameraCondition": "RainOnLens",
  "Severity": 6
}
