{
  "Scene": "Urban",
  "TimeOfDay": "Daytime",
  "Weather": "Rainy",
  "RoadConditions": "Wet",
  "LaneInformation": {
    "NumberOfLanes": "2",
    "LaneMarkings": "LaneVisible",
    "SpecialLanes": [
      "Street Parking"
    ]
  },
  "TrafficSigns": {
    "TrafficSignsTypes": [
      "Traffic Light"
    ],
    "TrafficSignsVisibility": "SignVisible",
    "TrafficLightState": "Red"
  },
  "Vehicles": {
    "TotalNumber": "MultipleVehicles",
    "VehicleTypes": [
      "Sedan",
      "SUV",
      "Van"
    ],
    "InMotion": [
      "False"
    ],
    "States": [
      "Parked",
      "Stopped at Intersection"
    ]
  },
  "Pedestrians": [
    "NoPed"
  ],
  "Directionality": "Two-Way",
  "Visibility": {
    "General": "Reduced",
    "SpecificImpairments": [
      "Camera Glare"
    ]
  },
  "Ego-Vehicle": {
    "Direction": "EgoForward",
    "Maneuver": "EgoMoving"
  },
  "CameraCondition": "Glare",
  "Severity": 6
}
